depin/__init__.py
depin/_internal/container.py
depin/_internal/exceptions.py
depin/_internal/helpers.py
depin/_internal/request_scope.py
depin/_internal/types.py
depin/_internal/wraps.py
depin/extensions/fastapi.py
pydepin-0.1.7.dist-info/METADATA
pydepin-0.1.7.dist-info/WHEEL
pydepin-0.1.7.dist-info/top_level.txt
pydepin-0.1.7.dist-info/RECORD
