Metadata-Version: 2.4
Name: pydepin
Version: 0.1.7
Summary: Dependency injection package
Requires-Python: >=3.13
Requires-Dist: fastapi[standard]<1.0,>=0.95
